LICENSE
MANIFEST.in
README.md
pyproject.toml
setup.cfg
mdimechanic/__init__.py
mdimechanic/__main__.py
mdimechanic/_version.py
mdimechanic/cli.py
mdimechanic/cmd_build.py
mdimechanic/cmd_interactive.py
mdimechanic/cmd_report.py
mdimechanic/cmd_run.py
mdimechanic/cmd_rundriver.py
mdimechanic/commands.py
mdimechanic/mdi_standard.yaml
mdimechanic.egg-info/PKG-INFO
mdimechanic.egg-info/SOURCES.txt
mdimechanic.egg-info/dependency_links.txt
mdimechanic.egg-info/entry_points.txt
mdimechanic.egg-info/not-zip-safe
mdimechanic.egg-info/requires.txt
mdimechanic.egg-info/top_level.txt
mdimechanic/data/README.md
mdimechanic/data/look_and_say.dat
mdimechanic/docker/Dockerfile
mdimechanic/docker/clean.sh
mdimechanic/docker/base/Dockerfile
mdimechanic/docker/base/docker-entrypoint.sh
mdimechanic/docker/mpi/docker-compose.yml
mdimechanic/docker/mpi/mdi_appfile
mdimechanic/docker/mpi_nvidia/docker-compose.yml
mdimechanic/docker/mpi_nvidia/mdi_appfile
mdimechanic/docker/run/docker-compose.yml
mdimechanic/docker/run_nvidia/docker-compose.yml
mdimechanic/docker/ssh/config
mdimechanic/docker/tcp/docker-compose.yml
mdimechanic/docker/tcp_nvidia/docker-compose.yml
mdimechanic/drivers/min_driver.py
mdimechanic/projects/enginereport/.gitignore
mdimechanic/projects/enginereport/mdimechanic.yml
mdimechanic/projects/enginereport/docker/Dockerfile
mdimechanic/report/README.base
mdimechanic/report/base_report/badges/-failing-red.svg
mdimechanic/report/base_report/badges/-working-success.svg
mdimechanic/report/base_report/badges/box-blue.svg
mdimechanic/report/base_report/badges/box-brightgreen.svg
mdimechanic/report/base_report/badges/box-green.svg
mdimechanic/report/base_report/badges/box-lightgray.svg
mdimechanic/report/base_report/badges/box-orange.svg
mdimechanic/report/base_report/badges/box-red.svg
mdimechanic/report/base_report/badges/box-yellow.svg
mdimechanic/report/base_report/badges/box-yellowgreen.svg
mdimechanic/report/base_report/dynamic_badges/step_engine_build.svg
mdimechanic/report/base_report/dynamic_badges/step_mdi_nodes.svg
mdimechanic/report/base_report/dynamic_badges/step_min_engine.svg
mdimechanic/report/base_report/dynamic_badges/step_unsupported.svg
mdimechanic/report/base_report/graphs/node-report.gv.svg
