Metadata-Version: 2.1
Name: mdimechanic
Version: 0.4.2
Summary: A tool for testing and developing MDI-enabled projects.
Author-email: Taylor Barnes <mdi@molssi.org>
License: BSD-3-Clause
Requires-Python: >=3.8
License-File: LICENSE
Requires-Dist: PyYAML>=5.0
Provides-Extra: test
Requires-Dist: pytest>=6.1.2; extra == "test"
Requires-Dist: pytest-runner; extra == "test"
